{
    "prettier.arrowParens": "always",
    "prettier.bracketSpacing": true,
    "prettier.configPath": "./prettierrc.json",
    "prettier.embeddedLanguageFormatting": "auto",
    "prettier.enable": true,
    "prettier.enableDebugLogs": false,
    "prettier.endOfLine": "lf",
    "prettier.htmlWhitespaceSensitivity": "css",
    "prettier.ignorePath": ".prettierignore",
    "prettier.insertPragma": false,
    "prettier.jsxBracketSameLine": false,
    "prettier.jsxSingleQuote": false,
    "prettier.printWidth": 100,
    "prettier.proseWrap": "preserve",
    "prettier.quoteProps": "as-needed",
    "prettier.requireConfig": true,
    "prettier.requirePragma": false,
    "prettier.resolveGlobalModules": false,
    "prettier.semi": true,
    "prettier.singleQuote": false,
    "prettier.tabWidth": 4,
    "prettier.trailingComma": "es5",
    "prettier.useEditorConfig": true,
    "prettier.useTabs": false,
    "prettier.vueIndentScriptAndStyle": false,
    "prettier.withNodeModules":false
}
